
{
  "neoforge:conditions": [
    {
      "type": "neoforge:mod_loaded",
      "modid": "blue_skies"
    }
  ],
  "type": "immersiveengineering:sawmill",
  "energy": 1600,
  "input": {
    "item": "blue_skies:starlit_bookshelf"
  },
  "result": {
    "basePredicate": {
      "item": "blue_skies:starlit_planks"
    },
    "count": 4
  },
  "secondaryOutputs": [
    {
      "tag": "forge:dusts/wood"
    },
    {
      "basePredicate": {
        "item": "minecraft:book"
      },
      "count": 3
    }
  ],
  "strippingSecondaries": []
}