{
  "type": "forge:conditional",
  "recipes": [
    {
      "conditions": [
        {
          "type": "forge:mod_loaded",
          "modid": "vinery"
        }
      ],
      "recipe": {
        "type": "immersiveengineering:cloche",
        "input": {
          "item": "vinery:savanna_grape_seeds_red"
        },
        "render": {
          "type": "bush",
          "block": "vinery:savanna_grape_bush_red"
        },
        "results": [
          {
            "item": "vinery:savanna_grapes_red"
          },
		  {
            "item": "vinery:savanna_grape_seeds_red"
          }
        ],
        "soil": {
          "item": "minecraft:dirt"
        },
        "time": 800
      }
    }
  ]
}