{
  "type": "forge:conditional",
  "recipes": [
    {
      "conditions": [
        {
          "type": "forge:mod_loaded",
          "modid": "naturesaura"
        }
      ],
      "recipe": {
        "type": "immersiveengineering:sawmill",
        "energy": 800,
        "input": {
          "item": "naturesaura:ancient_planks"
        },
        "result": {
          "count": 2,
          "item": "naturesaura:ancient_slab"
        },
        "secondaries": [
          {
            "output": {
              "tag": "forge:dusts/wood"
            },
            "stripping": false
          }
        ]
      }
    }
  ]
}
